pandasforce/__init__.py
pandasforce-0.0.10.dist-info/LICENSE
pandasforce-0.0.10.dist-info/METADATA
pandasforce-0.0.10.dist-info/WHEEL
pandasforce-0.0.10.dist-info/top_level.txt
pandasforce-0.0.10.dist-info/RECORD
