Metadata-Version: 2.1
Name: pandasforce
Version: 0.0.10
Summary: Integration of SalesForce and Pandas
Home-page: https://github.com/Jhruzik/pandasforce
Author: Joshua Hruzik
Author-email: joshua.hruzik@gmail.com
License: UNKNOWN
Platform: UNKNOWN
Classifier: Programming Language :: Python :: 3
Classifier: License :: OSI Approved :: MIT License
Classifier: Operating System :: OS Independent
Classifier: Intended Audience :: Developers
Classifier: Topic :: Database
Classifier: Topic :: Office/Business
Requires-Python: >=3.6
Requires-Dist: requests
Requires-Dist: pandas
